sphinx_filtered_toctree/__init__.py
sphinx_filtered_toctree/_version.py
sphinx_filtered_toctree/directive.py
sphinx_filtered_toctree-0.1.0.dist-info/licenses/LICENSE
sphinx_filtered_toctree-0.1.0.dist-info/METADATA
sphinx_filtered_toctree-0.1.0.dist-info/WHEEL
sphinx_filtered_toctree-0.1.0.dist-info/top_level.txt
sphinx_filtered_toctree-0.1.0.dist-info/RECORD
